askora/__init__.py
askora/cli.py
askora/factory.py
askora/models.py
askora/providers/__init__.py
askora/providers/base.py
askora/providers/claude_provider.py
askora/providers/deepseek_provider.py
askora/providers/ollama_provider.py
askora/providers/openai_provider.py
askora-0.0.2.dist-info/METADATA
askora-0.0.2.dist-info/WHEEL
askora-0.0.2.dist-info/entry_points.txt
askora-0.0.2.dist-info/top_level.txt
askora-0.0.2.dist-info/RECORD
