Metadata-Version: 2.4
Name: askora
Version: 0.0.2
Summary: A unified CLI for AI providers like OpenAI and Ollama
Author-email: jetroni <jetronsaiti@gmail.com>, FehmiHavziu <femi.havziu123@gmail.com>
License: MIT
Requires-Python: >=3.9
Requires-Dist: typer>=0.9
Requires-Dist: click>=8.1
Requires-Dist: rich>=13.0
Requires-Dist: openai>=1.0.0
Requires-Dist: anthropic>=0.64.0
Requires-Dist: pydantic>=1.10.22
